emailExtractorMBOX.py
EmailAddressExtractor_DS-0.1.3.dist-info/LICENSE
EmailAddressExtractor_DS-0.1.3.dist-info/METADATA
EmailAddressExtractor_DS-0.1.3.dist-info/WHEEL
EmailAddressExtractor_DS-0.1.3.dist-info/top_level.txt
EmailAddressExtractor_DS-0.1.3.dist-info/RECORD
