Metadata-Version: 2.1
Name: EmailAddressExtractor_DS
Version: 0.1.3
Summary: Extracts email addresses from MBOX files
Author-email: Deb Mishra <deb.mishra@daedal.email>
Project-URL: Homepage, https://bitbucket.org/daedalsystems/workspace/projects/microservices
Classifier: Programming Language :: Python :: 3
Classifier: License :: OSI Approved :: MIT License
Classifier: Operating System :: OS Independent
Requires-Python: >=3.7
License-File: LICENSE
